tweepipe/__init__.py
tweepipe/academic_client.py
tweepipe/base_client.py
tweepipe/follower.py
tweepipe/hydrating.py
tweepipe/lookup.py
tweepipe/searching.py
tweepipe/settings.py
tweepipe/streaming.py
tweepipe/base/__init__.py
tweepipe/base/follower.py
tweepipe/base/history.py
tweepipe/db/__init__.py
tweepipe/db/aggregation.py
tweepipe/db/db_client.py
tweepipe/db/db_schema.py
tweepipe/db/paginator.py
tweepipe/legacy/__init__.py
tweepipe/legacy/client.py
tweepipe/legacy/botspot/__init__.py
tweepipe/legacy/botspot/bfreq.py
tweepipe/legacy/botspot/botspot.py
tweepipe/legacy/botspot/example.py
tweepipe/utils/__init__.py
tweepipe/utils/credentials.py
tweepipe/utils/errors.py
tweepipe/utils/loader.py
tweepipe/utils/locations.py
tweepipe/utils/parallel.py
tweepipe/utils/query.py
tweepipe/utils/relation.py
tweepipe/utils/snowflake.py
tweepipe/utils/streaming_client.py
tweepipe/utils/tracker.py
tweepipe-0.0.1.dist-info/LICENSE
tweepipe-0.0.1.dist-info/METADATA
tweepipe-0.0.1.dist-info/WHEEL
tweepipe-0.0.1.dist-info/top_level.txt
tweepipe-0.0.1.dist-info/RECORD
