Metadata-Version: 2.1
Name: tweepipe
Version: 0.0.1
Summary: .
License: MIT
Requires-Python: >=3.8
License-File: LICENSE
